epot_test_deps/__init__.py
epot_test_deps-3.1.1.dist-info/WHEEL
epot_test_deps-3.1.1.dist-info/METADATA
epot_test_deps-3.1.1.dist-info/RECORD
