Metadata-Version: 2.1
Name: epot_test_deps
Version: 3.1.1
Summary: Deps of `epot-test`
Author-email: Conchylicultor <etils@google.com>
Requires-Python: >=3.8
